{
  "name": "Na kameni kámen",
  "author": "Brontosauři",
  "timing": "4/4",
  "chords": [
    "C",
    "Cmaj7",
    "D",
    "Em",
    "G"
  ],
  "text": [
    [
      "1. Jako {G}suchej,starej strom, jako {Cmaj7}všeničící hrom, jak v poli {G}tráva",
      "připa{G}dá mi ten náš svět, plnej {Cmaj7}řečí a čím {Em}víc, tím {D}líp se {G}mám."
    ],
    [
      "R: Budem {C}o něco se rvát, až tu {Em}nezůstane {D}stát na kameni {G}kámen,",
      "a jestli {Cmaj7}není žádnej Bůh, tak nás {Em}vezme země, {D}vzduch, no, a potom {G}amen."
    ],
    [
      "2. A to všechno proto jen, že pár pánů chce mít den bohatší králů,",
      "přes všechna slova, co z nich jdou, hrabou pro kuličku svou, jen pro tu svou."
    ],
    [
      "R: Budem o něco se rvát …"
    ],
    [
      "3. Možná jen se mi to zdá a po těžký noci přijde, přijde hezký ráno.",
      "Jaký bude, nevím sám, taky jsem si zvyk‘ na všechno kolem nás."
    ],
    [
      "R: Budem o něco se rvát …"
    ]
  ]
}